MANIFEST.in
README.txt
setup.cfg
setup.py
atreal/__init__.py
atreal.override.sharing.egg-info/PKG-INFO
atreal.override.sharing.egg-info/SOURCES.txt
atreal.override.sharing.egg-info/dependency_links.txt
atreal.override.sharing.egg-info/entry_points.txt
atreal.override.sharing.egg-info/namespace_packages.txt
atreal.override.sharing.egg-info/not-zip-safe
atreal.override.sharing.egg-info/requires.txt
atreal.override.sharing.egg-info/top_level.txt
atreal/override/__init__.py
atreal/override/sharing/__init__.py
atreal/override/sharing/configure.zcml
atreal/override/sharing/interfaces.py
atreal/override/sharing/browser/__init__.py
atreal/override/sharing/browser/atreal_override_sharing_icon.png
atreal/override/sharing/browser/configure.zcml
atreal/override/sharing/browser/controlpanel.py
atreal/override/sharing/browser/sharing.pt
atreal/override/sharing/browser/sharing.py
atreal/override/sharing/locales/atreal.override.sharing.pot
atreal/override/sharing/locales/fr/LC_MESSAGES/atreal.override.sharing.po
atreal/override/sharing/profiles/default/actionicons.xml
atreal/override/sharing/profiles/default/actions.xml
atreal/override/sharing/profiles/default/browserlayer.xml
atreal/override/sharing/profiles/default/controlpanel.xml
atreal/override/sharing/profiles/default/metadata.xml
atreal/override/sharing/profiles/default/rolemap.xml