Metadata-Version: 1.0
Name: atreal.override.sharing
Version: 1.0.0beta2
Summary: New UI for sharing roles tab in Plone
Home-page: http://www.atreal.net
Author: atReal
Author-email: contact@atreal.net
License: GPL
Platform: UNKNOWN
Classifier: Framework :: Plone
Classifier: Programming Language :: Python
Classifier: Topic :: Software Development :: Libraries :: Python Modules
